{
  "id": "env-prod-stockhub",
  "name": "Stockhub — Prod",
  "values": [
    {
      "key": "baseUrl",
      "value": "https://stockhub-back-bqf8e6fbf6dzd6gs.westeurope-01.azurewebsites.net",
      "type": "default",
      "enabled": true
    },
    {
      "key": "accessToken",
      "value": "",
      "type": "secret",
      "enabled": true
    },
    {
      "key": "stockId",
      "value": "1",
      "type": "default",
      "enabled": true
    },
    {
      "key": "itemId",
      "value": "1",
      "type": "default",
      "enabled": true
    }
  ],
  "_postman_variable_scope": "environment"
}
